Leviathan/__init__.py
Leviathan/interface.py
InterFaceTools-1.0.9.dist-info/LICENSE
InterFaceTools-1.0.9.dist-info/METADATA
InterFaceTools-1.0.9.dist-info/WHEEL
InterFaceTools-1.0.9.dist-info/top_level.txt
InterFaceTools-1.0.9.dist-info/RECORD
