Metadata-Version: 2.1
Name: InterFaceTools
Version: 1.0.9
Summary: allows for @interface class partail behavoiur decorator
Home-page: https://github.com/Leviathan-CE/InterfaceTools
Author: Leviathan-CE
Author-email: leviathanCE@outlook.com
Project-URL: bug Tracker , https://github.com/Leviathan-CE/InterfaceTools/issues
Project-URL: repository, https://github.com/Leviathan-CE/InterfaceTools
Classifier: Programming Language :: Python :: 3
Classifier: License :: OSI Approved :: MIT License
Classifier: Operating System :: OS Independent
Requires-Python: >=3.12
License-File: LICENSE
